wfrim_cin/__init__.py
wfrim_cin/decision.py
wfrim_cin/main.py
wfrim_cin-0.1.0.dist-info/LICENCE
wfrim_cin-0.1.0.dist-info/METADATA
wfrim_cin-0.1.0.dist-info/WHEEL
wfrim_cin-0.1.0.dist-info/RECORD
