Metadata-Version: 2.3
Name: wfrim_cin
Version: 0.1.0
Summary: Biblioteca Wfrim
License: MIT
Author: Victoria Pantoja, Wytoria Rodrigues, Rafaela Fernandes, Tiago Chacon
Requires-Python: >=3.10
Classifier: License :: OSI Approved :: MIT License
Classifier: Programming Language :: Python :: 3
Classifier: Programming Language :: Python :: 3.10
Classifier: Programming Language :: Python :: 3.11
Classifier: Programming Language :: Python :: 3.12
Classifier: Programming Language :: Python :: 3.13
